[
  {
    "id": "vo_hoc_intro",
    "name": "Võ học nhập môn",
    "category": "combat",
    "description": "Nền tảng võ thuật cơ bản.",
    "icon": "⚔️",
    "duration": 30,
    "prerequisites": [],
    "bonuses": { "strength": 2 },
    "bonusDescription": "+2% STR"
  },
  {
    "id": "vo_hoc_adv",
    "name": "Võ học nâng cao",
    "category": "combat",
    "description": "Kỹ thuật chiến đấu nâng cao, mở khóa rèn vũ khí.",
    "icon": "⚔️",
    "duration": 60,
    "prerequisites": ["vo_hoc_intro"],
    "bonuses": { "strength": 3, "gymBonus": 2 },
    "bonusDescription": "+3% STR, +2% Gym gains"
  },
  {
    "id": "dan_duoc_intro",
    "name": "Đan dược học nhập môn",
    "category": "alchemy",
    "description": "Học cách nhận biết và sử dụng đan dược.",
    "icon": "🧪",
    "duration": 30,
    "prerequisites": [],
    "bonuses": { "medEffectiveness": 10 },
    "bonusDescription": "+10% hiệu quả đan dược"
  },
  {
    "id": "dan_duoc_adv",
    "name": "Đan dược học nâng cao",
    "category": "alchemy",
    "description": "Chế tạo đan dược, luyện đan cơ bản.",
    "icon": "🧪",
    "duration": 60,
    "prerequisites": ["dan_duoc_intro"],
    "bonuses": { "medEffectiveness": 15, "hospitalReduction": 5 },
    "bonusDescription": "+15% hiệu quả đan dược, -5% thời gian tịnh dưỡng"
  },
  {
    "id": "ho_the_intro",
    "name": "Hộ thể thuật nhập môn",
    "category": "defense",
    "description": "Kỹ thuật phòng ngự cơ bản.",
    "icon": "🛡",
    "duration": 30,
    "prerequisites": [],
    "bonuses": { "defense": 2 },
    "bonusDescription": "+2% DEF"
  },
  {
    "id": "ho_the_adv",
    "name": "Hộ thể thuật nâng cao",
    "category": "defense",
    "description": "Rèn áo giáp, kỹ thuật hộ thể cao cấp.",
    "icon": "🛡",
    "duration": 60,
    "prerequisites": ["ho_the_intro"],
    "bonuses": { "defense": 3, "hospitalReduction": 5 },
    "bonusDescription": "+3% DEF, -5% thời gian tịnh dưỡng"
  },
  {
    "id": "than_phap_intro",
    "name": "Thân pháp nhập môn",
    "category": "agility",
    "description": "Khinh công cơ bản, di chuyển nhanh hơn.",
    "icon": "🏃",
    "duration": 30,
    "prerequisites": [],
    "bonuses": { "speed": 2 },
    "bonusDescription": "+2% SPD"
  },
  {
    "id": "than_phap_adv",
    "name": "Thân pháp nâng cao",
    "category": "agility",
    "description": "Khinh công cao cấp, né tránh tuyệt đỉnh.",
    "icon": "🏃",
    "duration": 60,
    "prerequisites": ["than_phap_intro"],
    "bonuses": { "speed": 3, "dodge": 2 },
    "bonusDescription": "+3% SPD, +2% Dodge"
  },
  {
    "id": "am_khi_intro",
    "name": "Ám khí thuật nhập môn",
    "category": "precision",
    "description": "Sử dụng ám khí, tăng chính xác.",
    "icon": "🎯",
    "duration": 30,
    "prerequisites": [],
    "bonuses": { "dexterity": 2 },
    "bonusDescription": "+2% DEX"
  },
  {
    "id": "am_khi_adv",
    "name": "Ám khí thuật nâng cao",
    "category": "precision",
    "description": "Ám khí sát thương, crit nâng cao.",
    "icon": "🎯",
    "duration": 60,
    "prerequisites": ["am_khi_intro"],
    "bonuses": { "dexterity": 3, "critChance": 3 },
    "bonusDescription": "+3% DEX, +3% Crit Chance"
  },
  {
    "id": "thien_van",
    "name": "Thiên văn học",
    "category": "knowledge",
    "description": "Hiểu Thiên Đạo, tăng kinh nghiệm thu được.",
    "icon": "📖",
    "duration": 45,
    "prerequisites": [],
    "bonuses": { "xpBonus": 5, "crimeSuccess": 5 },
    "bonusDescription": "+5% XP, +5% Crime success"
  }
]
